_cli_modules/__init__.py
_cli_modules/create.py
_cli_modules/option.py
modmaker/__init__.py
modmaker/__main__.py
modmaker/_cli.py
modmaker/_cli_core.py
modmaker/_common_utils.py
modmaker/_logger.py
modmaker/setup.py
modmaker/_cli_modules/__init__.py
modmaker/_cli_modules/create.py
modmaker/_cli_modules/option.py
modmaker/modmaker/__init__.py
modmaker/modmaker/_cli.py
modmaker/modmaker/_cli_core.py
modmaker/modmaker/_common_utils.py
modmaker/modmaker/_logger.py
modmaker/modmaker/_cli_modules/__init__.py
modmaker/modmaker/_cli_modules/create.py
modmaker/modmaker/_cli_modules/option.py
modmaker/modmaker/templates/__init__.py
modmaker/modmaker/templates/cli/__init__.py
modmaker/modmaker/templates/cli/tests/__init__.py
modmaker/modmaker/templates/cli/tests/test_cli.py
modmaker/modmaker/templates/cli/tests/test_commands.py
modmaker/modmaker/templates/cli/{{PROJECT_NAME}}/__init__.py
modmaker/modmaker/templates/cli/{{PROJECT_NAME}}/__main__.py
modmaker/modmaker/templates/cli/{{PROJECT_NAME}}/cli.py
modmaker/modmaker/templates/cli/{{PROJECT_NAME}}/commands.py
modmaker/templates/__init__.py
modmaker/templates/cli/__init__.py
modmaker/templates/cli/tests/__init__.py
modmaker/templates/cli/tests/test_cli.py
modmaker/templates/cli/tests/test_commands.py
modmaker/templates/cli/{{PROJECT_NAME}}/__init__.py
modmaker/templates/cli/{{PROJECT_NAME}}/__main__.py
modmaker/templates/cli/{{PROJECT_NAME}}/cli.py
modmaker/templates/cli/{{PROJECT_NAME}}/commands.py
modmaker/tests/__init__.py
modmaker/tests/test_bin_modmaker.py
modmaker/tests/test_cli.py
modmaker/tests/test_cli_core.py
modmaker/tests/test_common_utils.py
modmaker/tests/test_logger.py
templates/.DS_Store
templates/__init__.py
templates/cli/.gitignore
templates/cli/README.md
templates/cli/__init__.py
templates/cli/pyproject.toml
templates/cli/tests/__init__.py
templates/cli/tests/test_cli.py
templates/cli/tests/test_commands.py
templates/cli/{{PROJECT_NAME}}/__init__.py
templates/cli/{{PROJECT_NAME}}/cli.py
modmaker-0.1.10.dist-info/LICENSE
modmaker-0.1.10.dist-info/METADATA
modmaker-0.1.10.dist-info/WHEEL
modmaker-0.1.10.dist-info/entry_points.txt
modmaker-0.1.10.dist-info/top_level.txt
modmaker-0.1.10.dist-info/RECORD
