Metadata-Version: 2.2
Name: modmaker
Version: 0.1.10
Summary: Python project skeleton generator
Author: modmaker authors
Author-email: modmaker authors <avattathil@gmail.com>
License: Apache-2.0
Classifier: Programming Language :: Python :: 3
Classifier: License :: OSI Approved :: Apache Software License
Classifier: Operating System :: OS Independent
Requires-Python: >=3.9
License-File: LICENSE
Requires-Dist: requests
